roke/__init__.py
roke/__main__.py
roke/data/noun.txt
roke/main.py
roke-0.1.3.dist-info/METADATA
roke-0.1.3.dist-info/WHEEL
roke-0.1.3.dist-info/entry_points.txt
roke-0.1.3.dist-info/RECORD
