Metadata-Version: 2.1
Name: roke
Version: 0.1.3
Summary: A library to name and identify things
Home-page: https://github.com/ralsina/roke
License: MIT
Author: Roberto Alsina
Author-email: roberto.alsina@gmail.com
Requires-Python: >=3.8
Classifier: License :: OSI Approved :: MIT License
Classifier: Programming Language :: Python :: 3
Classifier: Programming Language :: Python :: 3.8
Classifier: Programming Language :: Python :: 3.9
Classifier: Programming Language :: Python :: 3.10
Classifier: Programming Language :: Python :: 3.11
Requires-Dist: click (>=8,<9)
